.gitignore
MANIFEST.in
README.md
requirements.txt
setup.py
test-requirements.txt
tox.ini
.github/workflows/test.yml
src/gretel_core.egg-info/PKG-INFO
src/gretel_core.egg-info/SOURCES.txt
src/gretel_core.egg-info/dependency_links.txt
src/gretel_core.egg-info/requires.txt
src/gretel_core.egg-info/top_level.txt
src/gretel_core/notifications/README.md
src/gretel_core/notifications/__init__.py
src/gretel_core/notifications/messages.py
src/gretel_core/notifications/providers.py
src/gretel_core/notifications/slack.py
src/gretel_core/synthetics/__init__.py
src/gretel_core/transformers/__init__.py
src/gretel_core/transformers/base.py
src/gretel_core/transformers/data_pipeline.py
src/gretel_core/transformers/data_restore_pipeline.py
src/gretel_core/transformers/data_transform_pipeline.py
src/gretel_core/transformers/fakers.py
src/gretel_core/transformers/masked.py
src/gretel_core/transformers/masked_restore.py
src/gretel_core/transformers/restore.py
src/gretel_core/transformers/string_mask.py
src/gretel_core/transformers/fpe/LICENSE
src/gretel_core/transformers/fpe/README.md
src/gretel_core/transformers/fpe/__init__.py
src/gretel_core/transformers/fpe/crypto_aes.py
src/gretel_core/transformers/fpe/fpe_ff1.py
src/gretel_core/transformers/fpe/fpe_prefix_cipher.py
src/gretel_core/transformers/transformers/__init__.py
src/gretel_core/transformers/transformers/bucket.py
src/gretel_core/transformers/transformers/combine.py
src/gretel_core/transformers/transformers/conditional.py
src/gretel_core/transformers/transformers/date_shift.py
src/gretel_core/transformers/transformers/drop.py
src/gretel_core/transformers/transformers/fake_constant.py
src/gretel_core/transformers/transformers/format.py
src/gretel_core/transformers/transformers/fpe_base.py
src/gretel_core/transformers/transformers/fpe_float.py
src/gretel_core/transformers/transformers/fpe_string.py
src/gretel_core/transformers/transformers/redact_with_char.py
src/gretel_core/transformers/transformers/redact_with_label.py
src/gretel_core/transformers/transformers/redact_with_string.py
src/gretel_core/transformers/transformers/secure_hash.py
tests/gretel_core/notifications/__init__.py
