Metadata-Version: 2.1
Name: gretel-core
Version: 0.1.0
Summary: Balance, anonymize, and share your data. With privacy guarantees.
Home-page: https://github.com/gretelai/gretel-core
Author: Gretel Labs, Inc.
Author-email: open-source@gretel.ai
License: UNKNOWN
Platform: UNKNOWN
Classifier: Programming Language :: Python :: 3
Classifier: Operating System :: POSIX :: Linux
Classifier: Operating System :: MacOS
Classifier: Operating System :: Microsoft :: Windows
Classifier: Topic :: Scientific/Engineering :: Artificial Intelligence
Requires-Python: >=3.6
